{"name":"Dlepzelter.GitHub.io","tagline":"Website for prettier display of github projects (under construction)","body":"[![Crimes against children in Chicago](https://github.com/dlepzelter/Chicago-crimes-against-kids/raw/master/crimesagainstkids.gif)](https://github.com/dlepzelter/Chicago-crimes-against-kids)\r\n[![Mortality in the U.S. and Sweden](https://github.com/dlepzelter/mortality/blob/master/mortality_swede.gif)](https://github.com/dlepzelter/mortality)","google":"","note":"Don't delete this file! It's used internally to help with page regeneration."}